weshi_h1/__init__.py
weshi_h1/main.py
weshi_h1-0.0.1.dist-info/METADATA
weshi_h1-0.0.1.dist-info/WHEEL
weshi_h1-0.0.1.dist-info/entry_points.txt
weshi_h1-0.0.1.dist-info/top_level.txt
weshi_h1-0.0.1.dist-info/RECORD
