Metadata-Version: 2.4
Name: weshi_h1
Version: 0.0.1
Summary: Opens Windows Calculator
Home-page: https://github.com/slvignesh05/weshi_h1
Author: Your Name
Author-email: your@email.com
License: MIT
Dynamic: author
Dynamic: author-email
Dynamic: description
Dynamic: description-content-type
Dynamic: home-page
Dynamic: license
Dynamic: summary
